[
  {
    "name": "大哥",
    "value": 4364
  },
  {
    "name": "体委",
    "value": 2288
  },
  {
    "name": "游戏",
    "value": 2288
  },
  {
    "name": "不赖",
    "value": 2238
  },
  {
    "name": "马哥",
    "value": 2064
  },
  {
    "name": "一把",
    "value": 2050
  },
  {
    "name": "大伙",
    "value": 1928
  },
  {
    "name": "小马",
    "value": 1860
  },
  {
    "name": "妹妹",
    "value": 1809
  },
  {
    "name": "晚上",
    "value": 1797
  },
  {
    "name": "兄弟",
    "value": 1705
  },
  {
    "name": "魔弹",
    "value": 1705
  },
  {
    "name": "天天",
    "value": 1683
  },
  {
    "name": "只能",
    "value": 1673
  },
  {
    "name": "一点",
    "value": 1646
  },
  {
    "name": "东西",
    "value": 1533
  },
  {
    "name": "记得",
    "value": 1485
  },
  {
    "name": "两个",
    "value": 1479
  },
  {
    "name": "明天",
    "value": 1475
  },
  {
    "name": "蛋哥",
    "value": 1475
  },
  {
    "name": "当时",
    "value": 1373
  },
  {
    "name": "喜欢",
    "value": 1355
  },
  {
    "name": "流泪",
    "value": 1354
  },
  {
    "name": "不到",
    "value": 1351
  },
  {
    "name": "昨天",
    "value": 1333
  },
  {
    "name": "回来",
    "value": 1277
  },
  {
    "name": "不想",
    "value": 1248
  },
  {
    "name": "时间",
    "value": 1248
  },
  {
    "name": "对面",
    "value": 1195
  },
  {
    "name": "学校",
    "value": 1159
  },
  {
    "name": "byd",
    "value": 1142
  },
  {
    "name": "全是",
    "value": 1135
  },
  {
    "name": "公司",
    "value": 1131
  },
  {
    "name": "几个",
    "value": 1127
  },
  {
    "name": "恶心",
    "value": 1112
  },
  {
    "name": "发现",
    "value": 1106
  },
  {
    "name": "无敌",
    "value": 1096
  },
  {
    "name": "同学",
    "value": 1065
  },
  {
    "name": "老师",
    "value": 1058
  },
  {
    "name": "re",
    "value": 1052
  },
  {
    "name": "猛攻",
    "value": 1024
  },
  {
    "name": "饶哥",
    "value": 1024
  },
  {
    "name": "丘序明",
    "value": 1022
  },
  {
    "name": "深圳",
    "value": 1018
  },
  {
    "name": "周姐",
    "value": 1008
  },
  {
    "name": "办法",
    "value": 1005
  },
  {
    "name": "吃饭",
    "value": 1005
  },
  {
    "name": "小时",
    "value": 1002
  },
  {
    "name": "不用",
    "value": 981
  },
  {
    "name": "有人",
    "value": 964
  },
  {
    "name": "下午",
    "value": 963
  },
  {
    "name": "队友",
    "value": 961
  },
  {
    "name": "一堆",
    "value": 959
  },
  {
    "name": "为啥",
    "value": 958
  },
  {
    "name": "ai",
    "value": 951
  },
  {
    "name": "哈哈哈",
    "value": 938
  },
  {
    "name": "学习",
    "value": 929
  },
  {
    "name": "三角洲",
    "value": 906
  },
  {
    "name": "哥们",
    "value": 905
  },
  {
    "name": "寿司",
    "value": 904
  },
  {
    "name": "估计",
    "value": 886
  },
  {
    "name": "三个",
    "value": 878
  },
  {
    "name": "玩意",
    "value": 866
  },
  {
    "name": "ok",
    "value": 847
  },
  {
    "name": "不好",
    "value": 845
  },
  {
    "name": "随便",
    "value": 840
  },
  {
    "name": "一哥",
    "value": 834
  },
  {
    "name": "我要",
    "value": 833
  },
  {
    "name": "今晚",
    "value": 821
  },
  {
    "name": "视频",
    "value": 817
  },
  {
    "name": "完蛋",
    "value": 815
  },
  {
    "name": "研究生",
    "value": 800
  },
  {
    "name": "情况",
    "value": 791
  },
  {
    "name": "一块",
    "value": 781
  },
  {
    "name": "卧槽",
    "value": 778
  },
  {
    "name": "神人",
    "value": 778
  },
  {
    "name": "上班",
    "value": 775
  },
  {
    "name": "nb",
    "value": 774
  },
  {
    "name": "睿哥",
    "value": 770
  },
  {
    "name": "干嘛",
    "value": 770
  },
  {
    "name": "电脑",
    "value": 764
  },
  {
    "name": "说话",
    "value": 747
  },
  {
    "name": "我测",
    "value": 746
  },
  {
    "name": "意思",
    "value": 734
  },
  {
    "name": "这是",
    "value": 731
  },
  {
    "name": "罕见",
    "value": 727
  },
  {
    "name": "不来",
    "value": 722
  },
  {
    "name": "到时候",
    "value": 716
  },
  {
    "name": "黄金",
    "value": 714
  },
  {
    "name": "还好",
    "value": 706
  },
  {
    "name": "打游戏",
    "value": 699
  },
  {
    "name": "有个",
    "value": 699
  },
  {
    "name": "开开",
    "value": 694
  },
  {
    "name": "白银",
    "value": 689
  },
  {
    "name": "压力",
    "value": 684
  },
  {
    "name": "美国",
    "value": 684
  },
  {
    "name": "玩游戏",
    "value": 682
  },
  {
    "name": "数据",
    "value": 679
  },
  {
    "name": "每次",
    "value": 677
  },
  {
    "name": "垃圾",
    "value": 661
  },
  {
    "name": "屏蔽",
    "value": 645
  },
  {
    "name": "竹马",
    "value": 643
  },
  {
    "name": "mico",
    "value": 639
  },
  {
    "name": "两把",
    "value": 635
  },
  {
    "name": "ayw",
    "value": 634
  },
  {
    "name": "上次",
    "value": 632
  },
  {
    "name": "宿舍",
    "value": 632
  },
  {
    "name": "我佛",
    "value": 626
  },
  {
    "name": "好看",
    "value": 621
  },
  {
    "name": "北京",
    "value": 619
  },
  {
    "name": "可惜",
    "value": 618
  },
  {
    "name": "睡觉",
    "value": 611
  },
  {
    "name": "回去",
    "value": 605
  },
  {
    "name": "开播",
    "value": 596
  },
  {
    "name": "别急",
    "value": 593
  },
  {
    "name": "手机",
    "value": 592
  },
  {
    "name": "狠狠",
    "value": 591
  },
  {
    "name": "波比",
    "value": 589
  },
  {
    "name": "地方",
    "value": 587
  },
  {
    "name": "舍友",
    "value": 587
  }
]